Metadata-Version: 1.0
Name: instafetch
Version: 0.1
Summary: Python package to get instagram data
Home-page: UNKNOWN
Author: Paras Sharmaa
Author-email: mail2paras.s@gmail.com
License: MIT
Keywords: Instagram API Python
Platform: UNKNOWN
